psg_recall/__init__.py
psg_recall/_modidx.py
psg_recall/recall.py
psg_recall/storage.py
psg_recall-0.0.4.dist-info/licenses/LICENSE
psg_recall-0.0.4.dist-info/METADATA
psg_recall-0.0.4.dist-info/WHEEL
psg_recall-0.0.4.dist-info/entry_points.txt
psg_recall-0.0.4.dist-info/top_level.txt
psg_recall-0.0.4.dist-info/RECORD
